#Signature file v4.1
#Version 5.0

CLSS public java.lang.Object
cons public init()
meth protected java.lang.Object clone() throws java.lang.CloneNotSupportedException
meth protected void finalize() throws java.lang.Throwable
meth public boolean equals(java.lang.Object)
meth public final java.lang.Class<?> getClass()
meth public final void notify()
meth public final void notifyAll()
meth public final void wait() throws java.lang.InterruptedException
meth public final void wait(long) throws java.lang.InterruptedException
meth public final void wait(long,int) throws java.lang.InterruptedException
meth public int hashCode()
meth public java.lang.String toString()

CLSS public abstract org.objectweb.asm.AnnotationVisitor
cons public init(int)
cons public init(int,org.objectweb.asm.AnnotationVisitor)
fld protected final int api
fld protected org.objectweb.asm.AnnotationVisitor av
meth public org.objectweb.asm.AnnotationVisitor visitAnnotation(java.lang.String,java.lang.String)
meth public org.objectweb.asm.AnnotationVisitor visitArray(java.lang.String)
meth public void visit(java.lang.String,java.lang.Object)
meth public void visitEnd()
meth public void visitEnum(java.lang.String,java.lang.String,java.lang.String)
supr java.lang.Object

CLSS public org.objectweb.asm.Attribute
cons protected init(java.lang.String)
fld public final java.lang.String type
meth protected org.objectweb.asm.Attribute read(org.objectweb.asm.ClassReader,int,int,char[],int,org.objectweb.asm.Label[])
meth protected org.objectweb.asm.ByteVector write(org.objectweb.asm.ClassWriter,byte[],int,int,int)
meth protected org.objectweb.asm.Label[] getLabels()
meth public boolean isCodeAttribute()
meth public boolean isUnknown()
supr java.lang.Object
hfds a,b

CLSS public org.objectweb.asm.ByteVector
cons public init()
cons public init(int)
meth public org.objectweb.asm.ByteVector putByte(int)
meth public org.objectweb.asm.ByteVector putByteArray(byte[],int,int)
meth public org.objectweb.asm.ByteVector putInt(int)
meth public org.objectweb.asm.ByteVector putLong(long)
meth public org.objectweb.asm.ByteVector putShort(int)
meth public org.objectweb.asm.ByteVector putUTF8(java.lang.String)
supr java.lang.Object
hfds a,b

CLSS public org.objectweb.asm.ClassReader
cons public init(byte[])
cons public init(byte[],int,int)
cons public init(java.io.InputStream) throws java.io.IOException
cons public init(java.lang.String) throws java.io.IOException
fld public final byte[] b
fld public final int header
fld public final static int EXPAND_FRAMES = 8
fld public final static int SKIP_CODE = 1
fld public final static int SKIP_DEBUG = 2
fld public final static int SKIP_FRAMES = 4
meth protected org.objectweb.asm.Label readLabel(int,org.objectweb.asm.Label[])
meth public int getAccess()
meth public int getItem(int)
meth public int getItemCount()
meth public int getMaxStringLength()
meth public int readByte(int)
meth public int readInt(int)
meth public int readUnsignedShort(int)
meth public java.lang.Object readConst(int,char[])
meth public java.lang.String getClassName()
meth public java.lang.String getSuperName()
meth public java.lang.String readClass(int,char[])
meth public java.lang.String readUTF8(int,char[])
meth public java.lang.String[] getInterfaces()
meth public long readLong(int)
meth public short readShort(int)
meth public void accept(org.objectweb.asm.ClassVisitor,int)
meth public void accept(org.objectweb.asm.ClassVisitor,org.objectweb.asm.Attribute[],int)
supr java.lang.Object
hfds a,c,d

CLSS public abstract org.objectweb.asm.ClassVisitor
cons public init(int)
cons public init(int,org.objectweb.asm.ClassVisitor)
fld protected final int api
fld protected org.objectweb.asm.ClassVisitor cv
meth public org.objectweb.asm.AnnotationVisitor visitAnnotation(java.lang.String,boolean)
meth public org.objectweb.asm.AnnotationVisitor visitTypeAnnotation(int,org.objectweb.asm.TypePath,java.lang.String,boolean)
meth public org.objectweb.asm.FieldVisitor visitField(int,java.lang.String,java.lang.String,java.lang.String,java.lang.Object)
meth public org.objectweb.asm.MethodVisitor visitMethod(int,java.lang.String,java.lang.String,java.lang.String,java.lang.String[])
meth public void visit(int,int,java.lang.String,java.lang.String,java.lang.String,java.lang.String[])
meth public void visitAttribute(org.objectweb.asm.Attribute)
meth public void visitEnd()
meth public void visitInnerClass(java.lang.String,java.lang.String,java.lang.String,int)
meth public void visitOuterClass(java.lang.String,java.lang.String,java.lang.String)
meth public void visitSource(java.lang.String,java.lang.String)
supr java.lang.Object

CLSS public org.objectweb.asm.ClassWriter
cons public init(int)
cons public init(org.objectweb.asm.ClassReader,int)
fld public final static int COMPUTE_FRAMES = 2
fld public final static int COMPUTE_MAXS = 1
meth protected java.lang.String getCommonSuperClass(java.lang.String,java.lang.String)
meth public !varargs int newInvokeDynamic(java.lang.String,java.lang.String,org.objectweb.asm.Handle,java.lang.Object[])
meth public byte[] toByteArray()
meth public final org.objectweb.asm.AnnotationVisitor visitAnnotation(java.lang.String,boolean)
meth public final org.objectweb.asm.AnnotationVisitor visitTypeAnnotation(int,org.objectweb.asm.TypePath,java.lang.String,boolean)
meth public final org.objectweb.asm.FieldVisitor visitField(int,java.lang.String,java.lang.String,java.lang.String,java.lang.Object)
meth public final org.objectweb.asm.MethodVisitor visitMethod(int,java.lang.String,java.lang.String,java.lang.String,java.lang.String[])
meth public final void visit(int,int,java.lang.String,java.lang.String,java.lang.String,java.lang.String[])
meth public final void visitAttribute(org.objectweb.asm.Attribute)
meth public final void visitEnd()
meth public final void visitInnerClass(java.lang.String,java.lang.String,java.lang.String,int)
meth public final void visitOuterClass(java.lang.String,java.lang.String,java.lang.String)
meth public final void visitSource(java.lang.String,java.lang.String)
meth public int newClass(java.lang.String)
meth public int newConst(java.lang.Object)
meth public int newField(java.lang.String,java.lang.String,java.lang.String)
meth public int newHandle(int,java.lang.String,java.lang.String,java.lang.String)
meth public int newMethod(java.lang.String,java.lang.String,java.lang.String,boolean)
meth public int newMethodType(java.lang.String)
meth public int newNameType(java.lang.String,java.lang.String)
meth public int newUTF8(java.lang.String)
supr org.objectweb.asm.ClassVisitor
hfds A,B,C,D,E,G,H,I,J,K,L,M,N,O,a,b,c,d,e,f,g,h,i,j,k,l,m,n,o,p,q,r,s,t,u,v,w,x,y,z

CLSS public abstract org.objectweb.asm.FieldVisitor
cons public init(int)
cons public init(int,org.objectweb.asm.FieldVisitor)
fld protected final int api
fld protected org.objectweb.asm.FieldVisitor fv
meth public org.objectweb.asm.AnnotationVisitor visitAnnotation(java.lang.String,boolean)
meth public org.objectweb.asm.AnnotationVisitor visitTypeAnnotation(int,org.objectweb.asm.TypePath,java.lang.String,boolean)
meth public void visitAttribute(org.objectweb.asm.Attribute)
meth public void visitEnd()
supr java.lang.Object

CLSS public final org.objectweb.asm.Handle
cons public init(int,java.lang.String,java.lang.String,java.lang.String)
meth public boolean equals(java.lang.Object)
meth public int getTag()
meth public int hashCode()
meth public java.lang.String getDesc()
meth public java.lang.String getName()
meth public java.lang.String getOwner()
meth public java.lang.String toString()
supr java.lang.Object
hfds a,b,c,d

CLSS public org.objectweb.asm.Label
cons public init()
fld public java.lang.Object info
meth public int getOffset()
meth public java.lang.String toString()
supr java.lang.Object
hfds a,b,c,d,e,f,g,h,i,j,k

CLSS public abstract org.objectweb.asm.MethodVisitor
cons public init(int)
cons public init(int,org.objectweb.asm.MethodVisitor)
fld protected final int api
fld protected org.objectweb.asm.MethodVisitor mv
meth public !varargs void visitInvokeDynamicInsn(java.lang.String,java.lang.String,org.objectweb.asm.Handle,java.lang.Object[])
meth public !varargs void visitTableSwitchInsn(int,int,org.objectweb.asm.Label,org.objectweb.asm.Label[])
meth public org.objectweb.asm.AnnotationVisitor visitAnnotation(java.lang.String,boolean)
meth public org.objectweb.asm.AnnotationVisitor visitAnnotationDefault()
meth public org.objectweb.asm.AnnotationVisitor visitInsnAnnotation(int,org.objectweb.asm.TypePath,java.lang.String,boolean)
meth public org.objectweb.asm.AnnotationVisitor visitLocalVariableAnnotation(int,org.objectweb.asm.TypePath,org.objectweb.asm.Label[],org.objectweb.asm.Label[],int[],java.lang.String,boolean)
meth public org.objectweb.asm.AnnotationVisitor visitParameterAnnotation(int,java.lang.String,boolean)
meth public org.objectweb.asm.AnnotationVisitor visitTryCatchAnnotation(int,org.objectweb.asm.TypePath,java.lang.String,boolean)
meth public org.objectweb.asm.AnnotationVisitor visitTypeAnnotation(int,org.objectweb.asm.TypePath,java.lang.String,boolean)
meth public void visitAttribute(org.objectweb.asm.Attribute)
meth public void visitCode()
meth public void visitEnd()
meth public void visitFieldInsn(int,java.lang.String,java.lang.String,java.lang.String)
meth public void visitFrame(int,int,java.lang.Object[],int,java.lang.Object[])
meth public void visitIincInsn(int,int)
meth public void visitInsn(int)
meth public void visitIntInsn(int,int)
meth public void visitJumpInsn(int,org.objectweb.asm.Label)
meth public void visitLabel(org.objectweb.asm.Label)
meth public void visitLdcInsn(java.lang.Object)
meth public void visitLineNumber(int,org.objectweb.asm.Label)
meth public void visitLocalVariable(java.lang.String,java.lang.String,java.lang.String,org.objectweb.asm.Label,org.objectweb.asm.Label,int)
meth public void visitLookupSwitchInsn(org.objectweb.asm.Label,int[],org.objectweb.asm.Label[])
meth public void visitMaxs(int,int)
meth public void visitMethodInsn(int,java.lang.String,java.lang.String,java.lang.String)
meth public void visitMethodInsn(int,java.lang.String,java.lang.String,java.lang.String,boolean)
meth public void visitMultiANewArrayInsn(java.lang.String,int)
meth public void visitParameter(java.lang.String,int)
meth public void visitTryCatchBlock(org.objectweb.asm.Label,org.objectweb.asm.Label,org.objectweb.asm.Label,java.lang.String)
meth public void visitTypeInsn(int,java.lang.String)
meth public void visitVarInsn(int,int)
supr java.lang.Object

CLSS public abstract interface org.objectweb.asm.Opcodes
fld public final static int AALOAD = 50
fld public final static int AASTORE = 83
fld public final static int ACC_ABSTRACT = 1024
fld public final static int ACC_ANNOTATION = 8192
fld public final static int ACC_BRIDGE = 64
fld public final static int ACC_DEPRECATED = 131072
fld public final static int ACC_ENUM = 16384
fld public final static int ACC_FINAL = 16
fld public final static int ACC_INTERFACE = 512
fld public final static int ACC_MANDATED = 32768
fld public final static int ACC_NATIVE = 256
fld public final static int ACC_PRIVATE = 2
fld public final static int ACC_PROTECTED = 4
fld public final static int ACC_PUBLIC = 1
fld public final static int ACC_STATIC = 8
fld public final static int ACC_STRICT = 2048
fld public final static int ACC_SUPER = 32
fld public final static int ACC_SYNCHRONIZED = 32
fld public final static int ACC_SYNTHETIC = 4096
fld public final static int ACC_TRANSIENT = 128
fld public final static int ACC_VARARGS = 128
fld public final static int ACC_VOLATILE = 64
fld public final static int ACONST_NULL = 1
fld public final static int ALOAD = 25
fld public final static int ANEWARRAY = 189
fld public final static int ARETURN = 176
fld public final static int ARRAYLENGTH = 190
fld public final static int ASM4 = 262144
fld public final static int ASM5 = 327680
fld public final static int ASTORE = 58
fld public final static int ATHROW = 191
fld public final static int BALOAD = 51
fld public final static int BASTORE = 84
fld public final static int BIPUSH = 16
fld public final static int CALOAD = 52
fld public final static int CASTORE = 85
fld public final static int CHECKCAST = 192
fld public final static int D2F = 144
fld public final static int D2I = 142
fld public final static int D2L = 143
fld public final static int DADD = 99
fld public final static int DALOAD = 49
fld public final static int DASTORE = 82
fld public final static int DCMPG = 152
fld public final static int DCMPL = 151
fld public final static int DCONST_0 = 14
fld public final static int DCONST_1 = 15
fld public final static int DDIV = 111
fld public final static int DLOAD = 24
fld public final static int DMUL = 107
fld public final static int DNEG = 119
fld public final static int DREM = 115
fld public final static int DRETURN = 175
fld public final static int DSTORE = 57
fld public final static int DSUB = 103
fld public final static int DUP = 89
fld public final static int DUP2 = 92
fld public final static int DUP2_X1 = 93
fld public final static int DUP2_X2 = 94
fld public final static int DUP_X1 = 90
fld public final static int DUP_X2 = 91
fld public final static int F2D = 141
fld public final static int F2I = 139
fld public final static int F2L = 140
fld public final static int FADD = 98
fld public final static int FALOAD = 48
fld public final static int FASTORE = 81
fld public final static int FCMPG = 150
fld public final static int FCMPL = 149
fld public final static int FCONST_0 = 11
fld public final static int FCONST_1 = 12
fld public final static int FCONST_2 = 13
fld public final static int FDIV = 110
fld public final static int FLOAD = 23
fld public final static int FMUL = 106
fld public final static int FNEG = 118
fld public final static int FREM = 114
fld public final static int FRETURN = 174
fld public final static int FSTORE = 56
fld public final static int FSUB = 102
fld public final static int F_APPEND = 1
fld public final static int F_CHOP = 2
fld public final static int F_FULL = 0
fld public final static int F_NEW = -1
fld public final static int F_SAME = 3
fld public final static int F_SAME1 = 4
fld public final static int GETFIELD = 180
fld public final static int GETSTATIC = 178
fld public final static int GOTO = 167
fld public final static int H_GETFIELD = 1
fld public final static int H_GETSTATIC = 2
fld public final static int H_INVOKEINTERFACE = 9
fld public final static int H_INVOKESPECIAL = 7
fld public final static int H_INVOKESTATIC = 6
fld public final static int H_INVOKEVIRTUAL = 5
fld public final static int H_NEWINVOKESPECIAL = 8
fld public final static int H_PUTFIELD = 3
fld public final static int H_PUTSTATIC = 4
fld public final static int I2B = 145
fld public final static int I2C = 146
fld public final static int I2D = 135
fld public final static int I2F = 134
fld public final static int I2L = 133
fld public final static int I2S = 147
fld public final static int IADD = 96
fld public final static int IALOAD = 46
fld public final static int IAND = 126
fld public final static int IASTORE = 79
fld public final static int ICONST_0 = 3
fld public final static int ICONST_1 = 4
fld public final static int ICONST_2 = 5
fld public final static int ICONST_3 = 6
fld public final static int ICONST_4 = 7
fld public final static int ICONST_5 = 8
fld public final static int ICONST_M1 = 2
fld public final static int IDIV = 108
fld public final static int IFEQ = 153
fld public final static int IFGE = 156
fld public final static int IFGT = 157
fld public final static int IFLE = 158
fld public final static int IFLT = 155
fld public final static int IFNE = 154
fld public final static int IFNONNULL = 199
fld public final static int IFNULL = 198
fld public final static int IF_ACMPEQ = 165
fld public final static int IF_ACMPNE = 166
fld public final static int IF_ICMPEQ = 159
fld public final static int IF_ICMPGE = 162
fld public final static int IF_ICMPGT = 163
fld public final static int IF_ICMPLE = 164
fld public final static int IF_ICMPLT = 161
fld public final static int IF_ICMPNE = 160
fld public final static int IINC = 132
fld public final static int ILOAD = 21
fld public final static int IMUL = 104
fld public final static int INEG = 116
fld public final static int INSTANCEOF = 193
fld public final static int INVOKEDYNAMIC = 186
fld public final static int INVOKEINTERFACE = 185
fld public final static int INVOKESPECIAL = 183
fld public final static int INVOKESTATIC = 184
fld public final static int INVOKEVIRTUAL = 182
fld public final static int IOR = 128
fld public final static int IREM = 112
fld public final static int IRETURN = 172
fld public final static int ISHL = 120
fld public final static int ISHR = 122
fld public final static int ISTORE = 54
fld public final static int ISUB = 100
fld public final static int IUSHR = 124
fld public final static int IXOR = 130
fld public final static int JSR = 168
fld public final static int L2D = 138
fld public final static int L2F = 137
fld public final static int L2I = 136
fld public final static int LADD = 97
fld public final static int LALOAD = 47
fld public final static int LAND = 127
fld public final static int LASTORE = 80
fld public final static int LCMP = 148
fld public final static int LCONST_0 = 9
fld public final static int LCONST_1 = 10
fld public final static int LDC = 18
fld public final static int LDIV = 109
fld public final static int LLOAD = 22
fld public final static int LMUL = 105
fld public final static int LNEG = 117
fld public final static int LOOKUPSWITCH = 171
fld public final static int LOR = 129
fld public final static int LREM = 113
fld public final static int LRETURN = 173
fld public final static int LSHL = 121
fld public final static int LSHR = 123
fld public final static int LSTORE = 55
fld public final static int LSUB = 101
fld public final static int LUSHR = 125
fld public final static int LXOR = 131
fld public final static int MONITORENTER = 194
fld public final static int MONITOREXIT = 195
fld public final static int MULTIANEWARRAY = 197
fld public final static int NEW = 187
fld public final static int NEWARRAY = 188
fld public final static int NOP = 0
fld public final static int POP = 87
fld public final static int POP2 = 88
fld public final static int PUTFIELD = 181
fld public final static int PUTSTATIC = 179
fld public final static int RET = 169
fld public final static int RETURN = 177
fld public final static int SALOAD = 53
fld public final static int SASTORE = 86
fld public final static int SIPUSH = 17
fld public final static int SWAP = 95
fld public final static int TABLESWITCH = 170
fld public final static int T_BOOLEAN = 4
fld public final static int T_BYTE = 8
fld public final static int T_CHAR = 5
fld public final static int T_DOUBLE = 7
fld public final static int T_FLOAT = 6
fld public final static int T_INT = 10
fld public final static int T_LONG = 11
fld public final static int T_SHORT = 9
fld public final static int V1_1 = 196653
fld public final static int V1_2 = 46
fld public final static int V1_3 = 47
fld public final static int V1_4 = 48
fld public final static int V1_5 = 49
fld public final static int V1_6 = 50
fld public final static int V1_7 = 51
fld public final static int V1_8 = 52
fld public final static java.lang.Integer DOUBLE
fld public final static java.lang.Integer FLOAT
fld public final static java.lang.Integer INTEGER
fld public final static java.lang.Integer LONG
fld public final static java.lang.Integer NULL
fld public final static java.lang.Integer TOP
fld public final static java.lang.Integer UNINITIALIZED_THIS

CLSS public org.objectweb.asm.Type
fld public final static int ARRAY = 9
fld public final static int BOOLEAN = 1
fld public final static int BYTE = 3
fld public final static int CHAR = 2
fld public final static int DOUBLE = 8
fld public final static int FLOAT = 6
fld public final static int INT = 5
fld public final static int LONG = 7
fld public final static int METHOD = 11
fld public final static int OBJECT = 10
fld public final static int SHORT = 4
fld public final static int VOID = 0
fld public final static org.objectweb.asm.Type BOOLEAN_TYPE
fld public final static org.objectweb.asm.Type BYTE_TYPE
fld public final static org.objectweb.asm.Type CHAR_TYPE
fld public final static org.objectweb.asm.Type DOUBLE_TYPE
fld public final static org.objectweb.asm.Type FLOAT_TYPE
fld public final static org.objectweb.asm.Type INT_TYPE
fld public final static org.objectweb.asm.Type LONG_TYPE
fld public final static org.objectweb.asm.Type SHORT_TYPE
fld public final static org.objectweb.asm.Type VOID_TYPE
meth public !varargs static java.lang.String getMethodDescriptor(org.objectweb.asm.Type,org.objectweb.asm.Type[])
meth public !varargs static org.objectweb.asm.Type getMethodType(org.objectweb.asm.Type,org.objectweb.asm.Type[])
meth public boolean equals(java.lang.Object)
meth public int getArgumentsAndReturnSizes()
meth public int getDimensions()
meth public int getOpcode(int)
meth public int getSize()
meth public int getSort()
meth public int hashCode()
meth public java.lang.String getClassName()
meth public java.lang.String getDescriptor()
meth public java.lang.String getInternalName()
meth public java.lang.String toString()
meth public org.objectweb.asm.Type getElementType()
meth public org.objectweb.asm.Type getReturnType()
meth public org.objectweb.asm.Type[] getArgumentTypes()
meth public static int getArgumentsAndReturnSizes(java.lang.String)
meth public static java.lang.String getConstructorDescriptor(java.lang.reflect.Constructor)
meth public static java.lang.String getDescriptor(java.lang.Class)
meth public static java.lang.String getInternalName(java.lang.Class)
meth public static java.lang.String getMethodDescriptor(java.lang.reflect.Method)
meth public static org.objectweb.asm.Type getMethodType(java.lang.String)
meth public static org.objectweb.asm.Type getObjectType(java.lang.String)
meth public static org.objectweb.asm.Type getReturnType(java.lang.String)
meth public static org.objectweb.asm.Type getReturnType(java.lang.reflect.Method)
meth public static org.objectweb.asm.Type getType(java.lang.Class)
meth public static org.objectweb.asm.Type getType(java.lang.String)
meth public static org.objectweb.asm.Type getType(java.lang.reflect.Constructor)
meth public static org.objectweb.asm.Type getType(java.lang.reflect.Method)
meth public static org.objectweb.asm.Type[] getArgumentTypes(java.lang.String)
meth public static org.objectweb.asm.Type[] getArgumentTypes(java.lang.reflect.Method)
supr java.lang.Object
hfds a,b,c,d

CLSS public org.objectweb.asm.TypePath
fld public final static int ARRAY_ELEMENT = 0
fld public final static int INNER_TYPE = 1
fld public final static int TYPE_ARGUMENT = 3
fld public final static int WILDCARD_BOUND = 2
meth public int getLength()
meth public int getStep(int)
meth public int getStepArgument(int)
meth public java.lang.String toString()
meth public static org.objectweb.asm.TypePath fromString(java.lang.String)
supr java.lang.Object
hfds a,b

CLSS public org.objectweb.asm.TypeReference
cons public init(int)
fld public final static int CAST = 71
fld public final static int CLASS_EXTENDS = 16
fld public final static int CLASS_TYPE_PARAMETER = 0
fld public final static int CLASS_TYPE_PARAMETER_BOUND = 17
fld public final static int CONSTRUCTOR_INVOCATION_TYPE_ARGUMENT = 72
fld public final static int CONSTRUCTOR_REFERENCE = 69
fld public final static int CONSTRUCTOR_REFERENCE_TYPE_ARGUMENT = 74
fld public final static int EXCEPTION_PARAMETER = 66
fld public final static int FIELD = 19
fld public final static int INSTANCEOF = 67
fld public final static int LOCAL_VARIABLE = 64
fld public final static int METHOD_FORMAL_PARAMETER = 22
fld public final static int METHOD_INVOCATION_TYPE_ARGUMENT = 73
fld public final static int METHOD_RECEIVER = 21
fld public final static int METHOD_REFERENCE = 70
fld public final static int METHOD_REFERENCE_TYPE_ARGUMENT = 75
fld public final static int METHOD_RETURN = 20
fld public final static int METHOD_TYPE_PARAMETER = 1
fld public final static int METHOD_TYPE_PARAMETER_BOUND = 18
fld public final static int NEW = 68
fld public final static int RESOURCE_VARIABLE = 65
fld public final static int THROWS = 23
meth public int getExceptionIndex()
meth public int getFormalParameterIndex()
meth public int getSort()
meth public int getSuperTypeIndex()
meth public int getTryCatchBlockIndex()
meth public int getTypeArgumentIndex()
meth public int getTypeParameterBoundIndex()
meth public int getTypeParameterIndex()
meth public int getValue()
meth public static org.objectweb.asm.TypeReference newExceptionReference(int)
meth public static org.objectweb.asm.TypeReference newFormalParameterReference(int)
meth public static org.objectweb.asm.TypeReference newSuperTypeReference(int)
meth public static org.objectweb.asm.TypeReference newTryCatchReference(int)
meth public static org.objectweb.asm.TypeReference newTypeArgumentReference(int,int)
meth public static org.objectweb.asm.TypeReference newTypeParameterBoundReference(int,int,int)
meth public static org.objectweb.asm.TypeReference newTypeParameterReference(int,int)
meth public static org.objectweb.asm.TypeReference newTypeReference(int)
supr java.lang.Object
hfds a

CLSS public org.objectweb.asm.signature.SignatureReader
cons public init(java.lang.String)
meth public void accept(org.objectweb.asm.signature.SignatureVisitor)
meth public void acceptType(org.objectweb.asm.signature.SignatureVisitor)
supr java.lang.Object
hfds a

CLSS public abstract org.objectweb.asm.signature.SignatureVisitor
cons public init(int)
fld protected final int api
fld public final static char EXTENDS = '+'
fld public final static char INSTANCEOF = '='
fld public final static char SUPER = '-'
meth public org.objectweb.asm.signature.SignatureVisitor visitArrayType()
meth public org.objectweb.asm.signature.SignatureVisitor visitClassBound()
meth public org.objectweb.asm.signature.SignatureVisitor visitExceptionType()
meth public org.objectweb.asm.signature.SignatureVisitor visitInterface()
meth public org.objectweb.asm.signature.SignatureVisitor visitInterfaceBound()
meth public org.objectweb.asm.signature.SignatureVisitor visitParameterType()
meth public org.objectweb.asm.signature.SignatureVisitor visitReturnType()
meth public org.objectweb.asm.signature.SignatureVisitor visitSuperclass()
meth public org.objectweb.asm.signature.SignatureVisitor visitTypeArgument(char)
meth public void visitBaseType(char)
meth public void visitClassType(java.lang.String)
meth public void visitEnd()
meth public void visitFormalTypeParameter(java.lang.String)
meth public void visitInnerClassType(java.lang.String)
meth public void visitTypeArgument()
meth public void visitTypeVariable(java.lang.String)
supr java.lang.Object

CLSS public org.objectweb.asm.signature.SignatureWriter
cons public init()
meth public java.lang.String toString()
meth public org.objectweb.asm.signature.SignatureVisitor visitArrayType()
meth public org.objectweb.asm.signature.SignatureVisitor visitClassBound()
meth public org.objectweb.asm.signature.SignatureVisitor visitExceptionType()
meth public org.objectweb.asm.signature.SignatureVisitor visitInterface()
meth public org.objectweb.asm.signature.SignatureVisitor visitInterfaceBound()
meth public org.objectweb.asm.signature.SignatureVisitor visitParameterType()
meth public org.objectweb.asm.signature.SignatureVisitor visitReturnType()
meth public org.objectweb.asm.signature.SignatureVisitor visitSuperclass()
meth public org.objectweb.asm.signature.SignatureVisitor visitTypeArgument(char)
meth public void visitBaseType(char)
meth public void visitClassType(java.lang.String)
meth public void visitEnd()
meth public void visitFormalTypeParameter(java.lang.String)
meth public void visitInnerClassType(java.lang.String)
meth public void visitTypeArgument()
meth public void visitTypeVariable(java.lang.String)
supr org.objectweb.asm.signature.SignatureVisitor
hfds a,b,c,d

