#Signature file v4.1
#Version 4.0

CLSS public java.lang.Object
cons public init()
meth protected java.lang.Object clone() throws java.lang.CloneNotSupportedException
meth protected void finalize() throws java.lang.Throwable
meth public boolean equals(java.lang.Object)
meth public final java.lang.Class<?> getClass()
meth public final void notify()
meth public final void notifyAll()
meth public final void wait() throws java.lang.InterruptedException
meth public final void wait(long) throws java.lang.InterruptedException
meth public final void wait(long,int) throws java.lang.InterruptedException
meth public int hashCode()
meth public java.lang.String toString()

CLSS public abstract org.objectweb.asm.AnnotationVisitor
cons public init(int)
cons public init(int,org.objectweb.asm.AnnotationVisitor)
fld protected final int api
fld protected org.objectweb.asm.AnnotationVisitor av
meth public org.objectweb.asm.AnnotationVisitor visitAnnotation(java.lang.String,java.lang.String)
meth public org.objectweb.asm.AnnotationVisitor visitArray(java.lang.String)
meth public void visit(java.lang.String,java.lang.Object)
meth public void visitEnd()
meth public void visitEnum(java.lang.String,java.lang.String,java.lang.String)
supr java.lang.Object

CLSS public abstract org.objectweb.asm.ClassVisitor
cons public init(int)
cons public init(int,org.objectweb.asm.ClassVisitor)
fld protected final int api
fld protected org.objectweb.asm.ClassVisitor cv
meth public org.objectweb.asm.AnnotationVisitor visitAnnotation(java.lang.String,boolean)
meth public org.objectweb.asm.FieldVisitor visitField(int,java.lang.String,java.lang.String,java.lang.String,java.lang.Object)
meth public org.objectweb.asm.MethodVisitor visitMethod(int,java.lang.String,java.lang.String,java.lang.String,java.lang.String[])
meth public void visit(int,int,java.lang.String,java.lang.String,java.lang.String,java.lang.String[])
meth public void visitAttribute(org.objectweb.asm.Attribute)
meth public void visitEnd()
meth public void visitInnerClass(java.lang.String,java.lang.String,java.lang.String,int)
meth public void visitOuterClass(java.lang.String,java.lang.String,java.lang.String)
meth public void visitSource(java.lang.String,java.lang.String)
supr java.lang.Object

CLSS public abstract org.objectweb.asm.FieldVisitor
cons public init(int)
cons public init(int,org.objectweb.asm.FieldVisitor)
fld protected final int api
fld protected org.objectweb.asm.FieldVisitor fv
meth public org.objectweb.asm.AnnotationVisitor visitAnnotation(java.lang.String,boolean)
meth public void visitAttribute(org.objectweb.asm.Attribute)
meth public void visitEnd()
supr java.lang.Object

CLSS public abstract org.objectweb.asm.MethodVisitor
cons public init(int)
cons public init(int,org.objectweb.asm.MethodVisitor)
fld protected final int api
fld protected org.objectweb.asm.MethodVisitor mv
meth public !varargs void visitInvokeDynamicInsn(java.lang.String,java.lang.String,org.objectweb.asm.Handle,java.lang.Object[])
meth public !varargs void visitTableSwitchInsn(int,int,org.objectweb.asm.Label,org.objectweb.asm.Label[])
meth public org.objectweb.asm.AnnotationVisitor visitAnnotation(java.lang.String,boolean)
meth public org.objectweb.asm.AnnotationVisitor visitAnnotationDefault()
meth public org.objectweb.asm.AnnotationVisitor visitParameterAnnotation(int,java.lang.String,boolean)
meth public void visitAttribute(org.objectweb.asm.Attribute)
meth public void visitCode()
meth public void visitEnd()
meth public void visitFieldInsn(int,java.lang.String,java.lang.String,java.lang.String)
meth public void visitFrame(int,int,java.lang.Object[],int,java.lang.Object[])
meth public void visitIincInsn(int,int)
meth public void visitInsn(int)
meth public void visitIntInsn(int,int)
meth public void visitJumpInsn(int,org.objectweb.asm.Label)
meth public void visitLabel(org.objectweb.asm.Label)
meth public void visitLdcInsn(java.lang.Object)
meth public void visitLineNumber(int,org.objectweb.asm.Label)
meth public void visitLocalVariable(java.lang.String,java.lang.String,java.lang.String,org.objectweb.asm.Label,org.objectweb.asm.Label,int)
meth public void visitLookupSwitchInsn(org.objectweb.asm.Label,int[],org.objectweb.asm.Label[])
meth public void visitMaxs(int,int)
meth public void visitMethodInsn(int,java.lang.String,java.lang.String,java.lang.String)
meth public void visitMultiANewArrayInsn(java.lang.String,int)
meth public void visitTryCatchBlock(org.objectweb.asm.Label,org.objectweb.asm.Label,org.objectweb.asm.Label,java.lang.String)
meth public void visitTypeInsn(int,java.lang.String)
meth public void visitVarInsn(int,int)
supr java.lang.Object

CLSS public abstract interface org.objectweb.asm.Opcodes
fld public final static int AALOAD = 50
fld public final static int AASTORE = 83
fld public final static int ACC_ABSTRACT = 1024
fld public final static int ACC_ANNOTATION = 8192
fld public final static int ACC_BRIDGE = 64
fld public final static int ACC_DEPRECATED = 131072
fld public final static int ACC_ENUM = 16384
fld public final static int ACC_FINAL = 16
fld public final static int ACC_INTERFACE = 512
fld public final static int ACC_NATIVE = 256
fld public final static int ACC_PRIVATE = 2
fld public final static int ACC_PROTECTED = 4
fld public final static int ACC_PUBLIC = 1
fld public final static int ACC_STATIC = 8
fld public final static int ACC_STRICT = 2048
fld public final static int ACC_SUPER = 32
fld public final static int ACC_SYNCHRONIZED = 32
fld public final static int ACC_SYNTHETIC = 4096
fld public final static int ACC_TRANSIENT = 128
fld public final static int ACC_VARARGS = 128
fld public final static int ACC_VOLATILE = 64
fld public final static int ACONST_NULL = 1
fld public final static int ALOAD = 25
fld public final static int ANEWARRAY = 189
fld public final static int ARETURN = 176
fld public final static int ARRAYLENGTH = 190
fld public final static int ASM4 = 262144
fld public final static int ASTORE = 58
fld public final static int ATHROW = 191
fld public final static int BALOAD = 51
fld public final static int BASTORE = 84
fld public final static int BIPUSH = 16
fld public final static int CALOAD = 52
fld public final static int CASTORE = 85
fld public final static int CHECKCAST = 192
fld public final static int D2F = 144
fld public final static int D2I = 142
fld public final static int D2L = 143
fld public final static int DADD = 99
fld public final static int DALOAD = 49
fld public final static int DASTORE = 82
fld public final static int DCMPG = 152
fld public final static int DCMPL = 151
fld public final static int DCONST_0 = 14
fld public final static int DCONST_1 = 15
fld public final static int DDIV = 111
fld public final static int DLOAD = 24
fld public final static int DMUL = 107
fld public final static int DNEG = 119
fld public final static int DREM = 115
fld public final static int DRETURN = 175
fld public final static int DSTORE = 57
fld public final static int DSUB = 103
fld public final static int DUP = 89
fld public final static int DUP2 = 92
fld public final static int DUP2_X1 = 93
fld public final static int DUP2_X2 = 94
fld public final static int DUP_X1 = 90
fld public final static int DUP_X2 = 91
fld public final static int F2D = 141
fld public final static int F2I = 139
fld public final static int F2L = 140
fld public final static int FADD = 98
fld public final static int FALOAD = 48
fld public final static int FASTORE = 81
fld public final static int FCMPG = 150
fld public final static int FCMPL = 149
fld public final static int FCONST_0 = 11
fld public final static int FCONST_1 = 12
fld public final static int FCONST_2 = 13
fld public final static int FDIV = 110
fld public final static int FLOAD = 23
fld public final static int FMUL = 106
fld public final static int FNEG = 118
fld public final static int FREM = 114
fld public final static int FRETURN = 174
fld public final static int FSTORE = 56
fld public final static int FSUB = 102
fld public final static int F_APPEND = 1
fld public final static int F_CHOP = 2
fld public final static int F_FULL = 0
fld public final static int F_NEW = -1
fld public final static int F_SAME = 3
fld public final static int F_SAME1 = 4
fld public final static int GETFIELD = 180
fld public final static int GETSTATIC = 178
fld public final static int GOTO = 167
fld public final static int H_GETFIELD = 1
fld public final static int H_GETSTATIC = 2
fld public final static int H_INVOKEINTERFACE = 9
fld public final static int H_INVOKESPECIAL = 7
fld public final static int H_INVOKESTATIC = 6
fld public final static int H_INVOKEVIRTUAL = 5
fld public final static int H_NEWINVOKESPECIAL = 8
fld public final static int H_PUTFIELD = 3
fld public final static int H_PUTSTATIC = 4
fld public final static int I2B = 145
fld public final static int I2C = 146
fld public final static int I2D = 135
fld public final static int I2F = 134
fld public final static int I2L = 133
fld public final static int I2S = 147
fld public final static int IADD = 96
fld public final static int IALOAD = 46
fld public final static int IAND = 126
fld public final static int IASTORE = 79
fld public final static int ICONST_0 = 3
fld public final static int ICONST_1 = 4
fld public final static int ICONST_2 = 5
fld public final static int ICONST_3 = 6
fld public final static int ICONST_4 = 7
fld public final static int ICONST_5 = 8
fld public final static int ICONST_M1 = 2
fld public final static int IDIV = 108
fld public final static int IFEQ = 153
fld public final static int IFGE = 156
fld public final static int IFGT = 157
fld public final static int IFLE = 158
fld public final static int IFLT = 155
fld public final static int IFNE = 154
fld public final static int IFNONNULL = 199
fld public final static int IFNULL = 198
fld public final static int IF_ACMPEQ = 165
fld public final static int IF_ACMPNE = 166
fld public final static int IF_ICMPEQ = 159
fld public final static int IF_ICMPGE = 162
fld public final static int IF_ICMPGT = 163
fld public final static int IF_ICMPLE = 164
fld public final static int IF_ICMPLT = 161
fld public final static int IF_ICMPNE = 160
fld public final static int IINC = 132
fld public final static int ILOAD = 21
fld public final static int IMUL = 104
fld public final static int INEG = 116
fld public final static int INSTANCEOF = 193
fld public final static int INVOKEDYNAMIC = 186
fld public final static int INVOKEINTERFACE = 185
fld public final static int INVOKESPECIAL = 183
fld public final static int INVOKESTATIC = 184
fld public final static int INVOKEVIRTUAL = 182
fld public final static int IOR = 128
fld public final static int IREM = 112
fld public final static int IRETURN = 172
fld public final static int ISHL = 120
fld public final static int ISHR = 122
fld public final static int ISTORE = 54
fld public final static int ISUB = 100
fld public final static int IUSHR = 124
fld public final static int IXOR = 130
fld public final static int JSR = 168
fld public final static int L2D = 138
fld public final static int L2F = 137
fld public final static int L2I = 136
fld public final static int LADD = 97
fld public final static int LALOAD = 47
fld public final static int LAND = 127
fld public final static int LASTORE = 80
fld public final static int LCMP = 148
fld public final static int LCONST_0 = 9
fld public final static int LCONST_1 = 10
fld public final static int LDC = 18
fld public final static int LDIV = 109
fld public final static int LLOAD = 22
fld public final static int LMUL = 105
fld public final static int LNEG = 117
fld public final static int LOOKUPSWITCH = 171
fld public final static int LOR = 129
fld public final static int LREM = 113
fld public final static int LRETURN = 173
fld public final static int LSHL = 121
fld public final static int LSHR = 123
fld public final static int LSTORE = 55
fld public final static int LSUB = 101
fld public final static int LUSHR = 125
fld public final static int LXOR = 131
fld public final static int MONITORENTER = 194
fld public final static int MONITOREXIT = 195
fld public final static int MULTIANEWARRAY = 197
fld public final static int NEW = 187
fld public final static int NEWARRAY = 188
fld public final static int NOP = 0
fld public final static int POP = 87
fld public final static int POP2 = 88
fld public final static int PUTFIELD = 181
fld public final static int PUTSTATIC = 179
fld public final static int RET = 169
fld public final static int RETURN = 177
fld public final static int SALOAD = 53
fld public final static int SASTORE = 86
fld public final static int SIPUSH = 17
fld public final static int SWAP = 95
fld public final static int TABLESWITCH = 170
fld public final static int T_BOOLEAN = 4
fld public final static int T_BYTE = 8
fld public final static int T_CHAR = 5
fld public final static int T_DOUBLE = 7
fld public final static int T_FLOAT = 6
fld public final static int T_INT = 10
fld public final static int T_LONG = 11
fld public final static int T_SHORT = 9
fld public final static int V1_1 = 196653
fld public final static int V1_2 = 46
fld public final static int V1_3 = 47
fld public final static int V1_4 = 48
fld public final static int V1_5 = 49
fld public final static int V1_6 = 50
fld public final static int V1_7 = 51
fld public final static java.lang.Integer DOUBLE
fld public final static java.lang.Integer FLOAT
fld public final static java.lang.Integer INTEGER
fld public final static java.lang.Integer LONG
fld public final static java.lang.Integer NULL
fld public final static java.lang.Integer TOP
fld public final static java.lang.Integer UNINITIALIZED_THIS

CLSS public org.objectweb.asm.xml.ASMContentHandler
cons public init(org.objectweb.asm.ClassVisitor)
fld protected java.util.Map labels
fld protected org.objectweb.asm.ClassVisitor cv
intf org.objectweb.asm.Opcodes
meth public final void endElement(java.lang.String,java.lang.String,java.lang.String) throws org.xml.sax.SAXException
meth public final void startElement(java.lang.String,java.lang.String,java.lang.String,org.xml.sax.Attributes) throws org.xml.sax.SAXException
supr org.xml.sax.helpers.DefaultHandler
hfds BASE,OPCODES,RULES,TYPES,match,stack

CLSS protected abstract org.objectweb.asm.xml.ASMContentHandler$Rule
cons protected init(org.objectweb.asm.xml.ASMContentHandler)
meth protected final int getAccess(java.lang.String)
meth protected final java.lang.Object getValue(java.lang.String,java.lang.String) throws org.xml.sax.SAXException
meth protected final org.objectweb.asm.Label getLabel(java.lang.Object)
meth protected final org.objectweb.asm.MethodVisitor getCodeVisitor()
meth public void begin(java.lang.String,org.xml.sax.Attributes) throws org.xml.sax.SAXException
meth public void end(java.lang.String)
supr java.lang.Object
hfds class$org$objectweb$asm$Handle,class$org$objectweb$asm$Type,this$0

CLSS public org.objectweb.asm.xml.Processor
cons public init(int,int,java.io.InputStream,java.io.OutputStream,javax.xml.transform.Source)
fld public final static int BYTECODE = 1
fld public final static int MULTI_XML = 2
fld public final static int SINGLE_XML = 3
meth protected void update(java.lang.Object,int)
meth public int process() throws java.io.IOException,javax.xml.transform.TransformerException,org.xml.sax.SAXException
meth public static void main(java.lang.String[]) throws java.lang.Exception
supr java.lang.Object
hfds SINGLE_XML_NAME,inRepresentation,input,n,outRepresentation,output,xslt

CLSS public org.objectweb.asm.xml.SAXAdapter
cons protected init(org.xml.sax.ContentHandler)
meth protected final void addElement(java.lang.String,org.xml.sax.Attributes)
meth protected final void addEnd(java.lang.String)
meth protected final void addStart(java.lang.String,org.xml.sax.Attributes)
meth protected org.xml.sax.ContentHandler getContentHandler()
meth protected void addDocumentEnd()
meth protected void addDocumentStart()
supr java.lang.Object
hfds h

CLSS public final org.objectweb.asm.xml.SAXAnnotationAdapter
cons protected init(int,org.objectweb.asm.xml.SAXAdapter,java.lang.String,int,java.lang.String,java.lang.String,int)
cons public init(org.objectweb.asm.xml.SAXAdapter,java.lang.String,int,int,java.lang.String)
cons public init(org.objectweb.asm.xml.SAXAdapter,java.lang.String,int,java.lang.String,java.lang.String)
meth public org.objectweb.asm.AnnotationVisitor visitAnnotation(java.lang.String,java.lang.String)
meth public org.objectweb.asm.AnnotationVisitor visitArray(java.lang.String)
meth public void visit(java.lang.String,java.lang.Object)
meth public void visitEnd()
meth public void visitEnum(java.lang.String,java.lang.String,java.lang.String)
supr org.objectweb.asm.AnnotationVisitor
hfds elementName,sa

CLSS public final org.objectweb.asm.xml.SAXClassAdapter
cons public init(org.xml.sax.ContentHandler,boolean)
meth public final void visitEnd()
meth public final void visitInnerClass(java.lang.String,java.lang.String,java.lang.String,int)
meth public org.objectweb.asm.AnnotationVisitor visitAnnotation(java.lang.String,boolean)
meth public org.objectweb.asm.FieldVisitor visitField(int,java.lang.String,java.lang.String,java.lang.String,java.lang.Object)
meth public org.objectweb.asm.MethodVisitor visitMethod(int,java.lang.String,java.lang.String,java.lang.String,java.lang.String[])
meth public void visit(int,int,java.lang.String,java.lang.String,java.lang.String,java.lang.String[])
meth public void visitOuterClass(java.lang.String,java.lang.String,java.lang.String)
meth public void visitSource(java.lang.String,java.lang.String)
supr org.objectweb.asm.ClassVisitor
hfds sa,singleDocument

CLSS public final org.objectweb.asm.xml.SAXCodeAdapter
cons public init(org.objectweb.asm.xml.SAXAdapter,int)
meth public !varargs final void visitTableSwitchInsn(int,int,org.objectweb.asm.Label,org.objectweb.asm.Label[])
meth public !varargs void visitInvokeDynamicInsn(java.lang.String,java.lang.String,org.objectweb.asm.Handle,java.lang.Object[])
meth public final void visitCode()
meth public final void visitFieldInsn(int,java.lang.String,java.lang.String,java.lang.String)
meth public final void visitIincInsn(int,int)
meth public final void visitInsn(int)
meth public final void visitIntInsn(int,int)
meth public final void visitJumpInsn(int,org.objectweb.asm.Label)
meth public final void visitLabel(org.objectweb.asm.Label)
meth public final void visitLdcInsn(java.lang.Object)
meth public final void visitLineNumber(int,org.objectweb.asm.Label)
meth public final void visitLookupSwitchInsn(org.objectweb.asm.Label,int[],org.objectweb.asm.Label[])
meth public final void visitMaxs(int,int)
meth public final void visitMethodInsn(int,java.lang.String,java.lang.String,java.lang.String)
meth public final void visitMultiANewArrayInsn(java.lang.String,int)
meth public final void visitTryCatchBlock(org.objectweb.asm.Label,org.objectweb.asm.Label,org.objectweb.asm.Label,java.lang.String)
meth public final void visitTypeInsn(int,java.lang.String)
meth public final void visitVarInsn(int,int)
meth public org.objectweb.asm.AnnotationVisitor visitAnnotation(java.lang.String,boolean)
meth public org.objectweb.asm.AnnotationVisitor visitAnnotationDefault()
meth public org.objectweb.asm.AnnotationVisitor visitParameterAnnotation(int,java.lang.String,boolean)
meth public void visitEnd()
meth public void visitFrame(int,int,java.lang.Object[],int,java.lang.Object[])
meth public void visitLocalVariable(java.lang.String,java.lang.String,java.lang.String,org.objectweb.asm.Label,org.objectweb.asm.Label,int)
supr org.objectweb.asm.MethodVisitor
hfds TYPES,labelNames,sa

CLSS public final org.objectweb.asm.xml.SAXFieldAdapter
cons public init(org.objectweb.asm.xml.SAXAdapter,org.xml.sax.Attributes)
meth public org.objectweb.asm.AnnotationVisitor visitAnnotation(java.lang.String,boolean)
meth public void visitEnd()
supr org.objectweb.asm.FieldVisitor
hfds sa

CLSS public abstract interface org.xml.sax.ContentHandler
meth public abstract void characters(char[],int,int) throws org.xml.sax.SAXException
meth public abstract void endDocument() throws org.xml.sax.SAXException
meth public abstract void endElement(java.lang.String,java.lang.String,java.lang.String) throws org.xml.sax.SAXException
meth public abstract void endPrefixMapping(java.lang.String) throws org.xml.sax.SAXException
meth public abstract void ignorableWhitespace(char[],int,int) throws org.xml.sax.SAXException
meth public abstract void processingInstruction(java.lang.String,java.lang.String) throws org.xml.sax.SAXException
meth public abstract void setDocumentLocator(org.xml.sax.Locator)
meth public abstract void skippedEntity(java.lang.String) throws org.xml.sax.SAXException
meth public abstract void startDocument() throws org.xml.sax.SAXException
meth public abstract void startElement(java.lang.String,java.lang.String,java.lang.String,org.xml.sax.Attributes) throws org.xml.sax.SAXException
meth public abstract void startPrefixMapping(java.lang.String,java.lang.String) throws org.xml.sax.SAXException

CLSS public abstract interface org.xml.sax.DTDHandler
meth public abstract void notationDecl(java.lang.String,java.lang.String,java.lang.String) throws org.xml.sax.SAXException
meth public abstract void unparsedEntityDecl(java.lang.String,java.lang.String,java.lang.String,java.lang.String) throws org.xml.sax.SAXException

CLSS public abstract interface org.xml.sax.EntityResolver
meth public abstract org.xml.sax.InputSource resolveEntity(java.lang.String,java.lang.String) throws java.io.IOException,org.xml.sax.SAXException

CLSS public abstract interface org.xml.sax.ErrorHandler
meth public abstract void error(org.xml.sax.SAXParseException) throws org.xml.sax.SAXException
meth public abstract void fatalError(org.xml.sax.SAXParseException) throws org.xml.sax.SAXException
meth public abstract void warning(org.xml.sax.SAXParseException) throws org.xml.sax.SAXException

CLSS public org.xml.sax.helpers.DefaultHandler
cons public init()
intf org.xml.sax.ContentHandler
intf org.xml.sax.DTDHandler
intf org.xml.sax.EntityResolver
intf org.xml.sax.ErrorHandler
meth public org.xml.sax.InputSource resolveEntity(java.lang.String,java.lang.String) throws java.io.IOException,org.xml.sax.SAXException
meth public void characters(char[],int,int) throws org.xml.sax.SAXException
meth public void endDocument() throws org.xml.sax.SAXException
meth public void endElement(java.lang.String,java.lang.String,java.lang.String) throws org.xml.sax.SAXException
meth public void endPrefixMapping(java.lang.String) throws org.xml.sax.SAXException
meth public void error(org.xml.sax.SAXParseException) throws org.xml.sax.SAXException
meth public void fatalError(org.xml.sax.SAXParseException) throws org.xml.sax.SAXException
meth public void ignorableWhitespace(char[],int,int) throws org.xml.sax.SAXException
meth public void notationDecl(java.lang.String,java.lang.String,java.lang.String) throws org.xml.sax.SAXException
meth public void processingInstruction(java.lang.String,java.lang.String) throws org.xml.sax.SAXException
meth public void setDocumentLocator(org.xml.sax.Locator)
meth public void skippedEntity(java.lang.String) throws org.xml.sax.SAXException
meth public void startDocument() throws org.xml.sax.SAXException
meth public void startElement(java.lang.String,java.lang.String,java.lang.String,org.xml.sax.Attributes) throws org.xml.sax.SAXException
meth public void startPrefixMapping(java.lang.String,java.lang.String) throws org.xml.sax.SAXException
meth public void unparsedEntityDecl(java.lang.String,java.lang.String,java.lang.String,java.lang.String) throws org.xml.sax.SAXException
meth public void warning(org.xml.sax.SAXParseException) throws org.xml.sax.SAXException
supr java.lang.Object

