#Signature file v4.1
#Version 4.0

CLSS public java.lang.Object
cons public init()
meth protected java.lang.Object clone() throws java.lang.CloneNotSupportedException
meth protected void finalize() throws java.lang.Throwable
meth public boolean equals(java.lang.Object)
meth public final java.lang.Class<?> getClass()
meth public final void notify()
meth public final void notifyAll()
meth public final void wait() throws java.lang.InterruptedException
meth public final void wait(long) throws java.lang.InterruptedException
meth public final void wait(long,int) throws java.lang.InterruptedException
meth public int hashCode()
meth public java.lang.String toString()

CLSS public abstract org.objectweb.asm.AnnotationVisitor
cons public init(int)
cons public init(int,org.objectweb.asm.AnnotationVisitor)
fld protected final int api
fld protected org.objectweb.asm.AnnotationVisitor av
meth public org.objectweb.asm.AnnotationVisitor visitAnnotation(java.lang.String,java.lang.String)
meth public org.objectweb.asm.AnnotationVisitor visitArray(java.lang.String)
meth public void visit(java.lang.String,java.lang.Object)
meth public void visitEnd()
meth public void visitEnum(java.lang.String,java.lang.String,java.lang.String)
supr java.lang.Object

CLSS public abstract org.objectweb.asm.ClassVisitor
cons public init(int)
cons public init(int,org.objectweb.asm.ClassVisitor)
fld protected final int api
fld protected org.objectweb.asm.ClassVisitor cv
meth public org.objectweb.asm.AnnotationVisitor visitAnnotation(java.lang.String,boolean)
meth public org.objectweb.asm.FieldVisitor visitField(int,java.lang.String,java.lang.String,java.lang.String,java.lang.Object)
meth public org.objectweb.asm.MethodVisitor visitMethod(int,java.lang.String,java.lang.String,java.lang.String,java.lang.String[])
meth public void visit(int,int,java.lang.String,java.lang.String,java.lang.String,java.lang.String[])
meth public void visitAttribute(org.objectweb.asm.Attribute)
meth public void visitEnd()
meth public void visitInnerClass(java.lang.String,java.lang.String,java.lang.String,int)
meth public void visitOuterClass(java.lang.String,java.lang.String,java.lang.String)
meth public void visitSource(java.lang.String,java.lang.String)
supr java.lang.Object

CLSS public abstract org.objectweb.asm.FieldVisitor
cons public init(int)
cons public init(int,org.objectweb.asm.FieldVisitor)
fld protected final int api
fld protected org.objectweb.asm.FieldVisitor fv
meth public org.objectweb.asm.AnnotationVisitor visitAnnotation(java.lang.String,boolean)
meth public void visitAttribute(org.objectweb.asm.Attribute)
meth public void visitEnd()
supr java.lang.Object

CLSS public abstract org.objectweb.asm.MethodVisitor
cons public init(int)
cons public init(int,org.objectweb.asm.MethodVisitor)
fld protected final int api
fld protected org.objectweb.asm.MethodVisitor mv
meth public !varargs void visitInvokeDynamicInsn(java.lang.String,java.lang.String,org.objectweb.asm.Handle,java.lang.Object[])
meth public !varargs void visitTableSwitchInsn(int,int,org.objectweb.asm.Label,org.objectweb.asm.Label[])
meth public org.objectweb.asm.AnnotationVisitor visitAnnotation(java.lang.String,boolean)
meth public org.objectweb.asm.AnnotationVisitor visitAnnotationDefault()
meth public org.objectweb.asm.AnnotationVisitor visitParameterAnnotation(int,java.lang.String,boolean)
meth public void visitAttribute(org.objectweb.asm.Attribute)
meth public void visitCode()
meth public void visitEnd()
meth public void visitFieldInsn(int,java.lang.String,java.lang.String,java.lang.String)
meth public void visitFrame(int,int,java.lang.Object[],int,java.lang.Object[])
meth public void visitIincInsn(int,int)
meth public void visitInsn(int)
meth public void visitIntInsn(int,int)
meth public void visitJumpInsn(int,org.objectweb.asm.Label)
meth public void visitLabel(org.objectweb.asm.Label)
meth public void visitLdcInsn(java.lang.Object)
meth public void visitLineNumber(int,org.objectweb.asm.Label)
meth public void visitLocalVariable(java.lang.String,java.lang.String,java.lang.String,org.objectweb.asm.Label,org.objectweb.asm.Label,int)
meth public void visitLookupSwitchInsn(org.objectweb.asm.Label,int[],org.objectweb.asm.Label[])
meth public void visitMaxs(int,int)
meth public void visitMethodInsn(int,java.lang.String,java.lang.String,java.lang.String)
meth public void visitMultiANewArrayInsn(java.lang.String,int)
meth public void visitTryCatchBlock(org.objectweb.asm.Label,org.objectweb.asm.Label,org.objectweb.asm.Label,java.lang.String)
meth public void visitTypeInsn(int,java.lang.String)
meth public void visitVarInsn(int,int)
supr java.lang.Object

CLSS public abstract interface org.objectweb.asm.Opcodes
fld public final static int AALOAD = 50
fld public final static int AASTORE = 83
fld public final static int ACC_ABSTRACT = 1024
fld public final static int ACC_ANNOTATION = 8192
fld public final static int ACC_BRIDGE = 64
fld public final static int ACC_DEPRECATED = 131072
fld public final static int ACC_ENUM = 16384
fld public final static int ACC_FINAL = 16
fld public final static int ACC_INTERFACE = 512
fld public final static int ACC_NATIVE = 256
fld public final static int ACC_PRIVATE = 2
fld public final static int ACC_PROTECTED = 4
fld public final static int ACC_PUBLIC = 1
fld public final static int ACC_STATIC = 8
fld public final static int ACC_STRICT = 2048
fld public final static int ACC_SUPER = 32
fld public final static int ACC_SYNCHRONIZED = 32
fld public final static int ACC_SYNTHETIC = 4096
fld public final static int ACC_TRANSIENT = 128
fld public final static int ACC_VARARGS = 128
fld public final static int ACC_VOLATILE = 64
fld public final static int ACONST_NULL = 1
fld public final static int ALOAD = 25
fld public final static int ANEWARRAY = 189
fld public final static int ARETURN = 176
fld public final static int ARRAYLENGTH = 190
fld public final static int ASM4 = 262144
fld public final static int ASTORE = 58
fld public final static int ATHROW = 191
fld public final static int BALOAD = 51
fld public final static int BASTORE = 84
fld public final static int BIPUSH = 16
fld public final static int CALOAD = 52
fld public final static int CASTORE = 85
fld public final static int CHECKCAST = 192
fld public final static int D2F = 144
fld public final static int D2I = 142
fld public final static int D2L = 143
fld public final static int DADD = 99
fld public final static int DALOAD = 49
fld public final static int DASTORE = 82
fld public final static int DCMPG = 152
fld public final static int DCMPL = 151
fld public final static int DCONST_0 = 14
fld public final static int DCONST_1 = 15
fld public final static int DDIV = 111
fld public final static int DLOAD = 24
fld public final static int DMUL = 107
fld public final static int DNEG = 119
fld public final static int DREM = 115
fld public final static int DRETURN = 175
fld public final static int DSTORE = 57
fld public final static int DSUB = 103
fld public final static int DUP = 89
fld public final static int DUP2 = 92
fld public final static int DUP2_X1 = 93
fld public final static int DUP2_X2 = 94
fld public final static int DUP_X1 = 90
fld public final static int DUP_X2 = 91
fld public final static int F2D = 141
fld public final static int F2I = 139
fld public final static int F2L = 140
fld public final static int FADD = 98
fld public final static int FALOAD = 48
fld public final static int FASTORE = 81
fld public final static int FCMPG = 150
fld public final static int FCMPL = 149
fld public final static int FCONST_0 = 11
fld public final static int FCONST_1 = 12
fld public final static int FCONST_2 = 13
fld public final static int FDIV = 110
fld public final static int FLOAD = 23
fld public final static int FMUL = 106
fld public final static int FNEG = 118
fld public final static int FREM = 114
fld public final static int FRETURN = 174
fld public final static int FSTORE = 56
fld public final static int FSUB = 102
fld public final static int F_APPEND = 1
fld public final static int F_CHOP = 2
fld public final static int F_FULL = 0
fld public final static int F_NEW = -1
fld public final static int F_SAME = 3
fld public final static int F_SAME1 = 4
fld public final static int GETFIELD = 180
fld public final static int GETSTATIC = 178
fld public final static int GOTO = 167
fld public final static int H_GETFIELD = 1
fld public final static int H_GETSTATIC = 2
fld public final static int H_INVOKEINTERFACE = 9
fld public final static int H_INVOKESPECIAL = 7
fld public final static int H_INVOKESTATIC = 6
fld public final static int H_INVOKEVIRTUAL = 5
fld public final static int H_NEWINVOKESPECIAL = 8
fld public final static int H_PUTFIELD = 3
fld public final static int H_PUTSTATIC = 4
fld public final static int I2B = 145
fld public final static int I2C = 146
fld public final static int I2D = 135
fld public final static int I2F = 134
fld public final static int I2L = 133
fld public final static int I2S = 147
fld public final static int IADD = 96
fld public final static int IALOAD = 46
fld public final static int IAND = 126
fld public final static int IASTORE = 79
fld public final static int ICONST_0 = 3
fld public final static int ICONST_1 = 4
fld public final static int ICONST_2 = 5
fld public final static int ICONST_3 = 6
fld public final static int ICONST_4 = 7
fld public final static int ICONST_5 = 8
fld public final static int ICONST_M1 = 2
fld public final static int IDIV = 108
fld public final static int IFEQ = 153
fld public final static int IFGE = 156
fld public final static int IFGT = 157
fld public final static int IFLE = 158
fld public final static int IFLT = 155
fld public final static int IFNE = 154
fld public final static int IFNONNULL = 199
fld public final static int IFNULL = 198
fld public final static int IF_ACMPEQ = 165
fld public final static int IF_ACMPNE = 166
fld public final static int IF_ICMPEQ = 159
fld public final static int IF_ICMPGE = 162
fld public final static int IF_ICMPGT = 163
fld public final static int IF_ICMPLE = 164
fld public final static int IF_ICMPLT = 161
fld public final static int IF_ICMPNE = 160
fld public final static int IINC = 132
fld public final static int ILOAD = 21
fld public final static int IMUL = 104
fld public final static int INEG = 116
fld public final static int INSTANCEOF = 193
fld public final static int INVOKEDYNAMIC = 186
fld public final static int INVOKEINTERFACE = 185
fld public final static int INVOKESPECIAL = 183
fld public final static int INVOKESTATIC = 184
fld public final static int INVOKEVIRTUAL = 182
fld public final static int IOR = 128
fld public final static int IREM = 112
fld public final static int IRETURN = 172
fld public final static int ISHL = 120
fld public final static int ISHR = 122
fld public final static int ISTORE = 54
fld public final static int ISUB = 100
fld public final static int IUSHR = 124
fld public final static int IXOR = 130
fld public final static int JSR = 168
fld public final static int L2D = 138
fld public final static int L2F = 137
fld public final static int L2I = 136
fld public final static int LADD = 97
fld public final static int LALOAD = 47
fld public final static int LAND = 127
fld public final static int LASTORE = 80
fld public final static int LCMP = 148
fld public final static int LCONST_0 = 9
fld public final static int LCONST_1 = 10
fld public final static int LDC = 18
fld public final static int LDIV = 109
fld public final static int LLOAD = 22
fld public final static int LMUL = 105
fld public final static int LNEG = 117
fld public final static int LOOKUPSWITCH = 171
fld public final static int LOR = 129
fld public final static int LREM = 113
fld public final static int LRETURN = 173
fld public final static int LSHL = 121
fld public final static int LSHR = 123
fld public final static int LSTORE = 55
fld public final static int LSUB = 101
fld public final static int LUSHR = 125
fld public final static int LXOR = 131
fld public final static int MONITORENTER = 194
fld public final static int MONITOREXIT = 195
fld public final static int MULTIANEWARRAY = 197
fld public final static int NEW = 187
fld public final static int NEWARRAY = 188
fld public final static int NOP = 0
fld public final static int POP = 87
fld public final static int POP2 = 88
fld public final static int PUTFIELD = 181
fld public final static int PUTSTATIC = 179
fld public final static int RET = 169
fld public final static int RETURN = 177
fld public final static int SALOAD = 53
fld public final static int SASTORE = 86
fld public final static int SIPUSH = 17
fld public final static int SWAP = 95
fld public final static int TABLESWITCH = 170
fld public final static int T_BOOLEAN = 4
fld public final static int T_BYTE = 8
fld public final static int T_CHAR = 5
fld public final static int T_DOUBLE = 7
fld public final static int T_FLOAT = 6
fld public final static int T_INT = 10
fld public final static int T_LONG = 11
fld public final static int T_SHORT = 9
fld public final static int V1_1 = 196653
fld public final static int V1_2 = 46
fld public final static int V1_3 = 47
fld public final static int V1_4 = 48
fld public final static int V1_5 = 49
fld public final static int V1_6 = 50
fld public final static int V1_7 = 51
fld public final static java.lang.Integer DOUBLE
fld public final static java.lang.Integer FLOAT
fld public final static java.lang.Integer INTEGER
fld public final static java.lang.Integer LONG
fld public final static java.lang.Integer NULL
fld public final static java.lang.Integer TOP
fld public final static java.lang.Integer UNINITIALIZED_THIS

CLSS public abstract org.objectweb.asm.commons.AdviceAdapter
cons protected init(int,org.objectweb.asm.MethodVisitor,int,java.lang.String,java.lang.String)
fld protected int methodAccess
fld protected java.lang.String methodDesc
intf org.objectweb.asm.Opcodes
meth protected void onMethodEnter()
meth protected void onMethodExit(int)
meth public !varargs void visitInvokeDynamicInsn(java.lang.String,java.lang.String,org.objectweb.asm.Handle,java.lang.Object[])
meth public !varargs void visitTableSwitchInsn(int,int,org.objectweb.asm.Label,org.objectweb.asm.Label[])
meth public void visitCode()
meth public void visitFieldInsn(int,java.lang.String,java.lang.String,java.lang.String)
meth public void visitInsn(int)
meth public void visitIntInsn(int,int)
meth public void visitJumpInsn(int,org.objectweb.asm.Label)
meth public void visitLabel(org.objectweb.asm.Label)
meth public void visitLdcInsn(java.lang.Object)
meth public void visitLookupSwitchInsn(org.objectweb.asm.Label,int[],org.objectweb.asm.Label[])
meth public void visitMethodInsn(int,java.lang.String,java.lang.String,java.lang.String)
meth public void visitMultiANewArrayInsn(java.lang.String,int)
meth public void visitTryCatchBlock(org.objectweb.asm.Label,org.objectweb.asm.Label,org.objectweb.asm.Label,java.lang.String)
meth public void visitTypeInsn(int,java.lang.String)
meth public void visitVarInsn(int,int)
supr org.objectweb.asm.commons.GeneratorAdapter
hfds OTHER,THIS,branches,constructor,stackFrame,superInitialized

CLSS public org.objectweb.asm.commons.AnalyzerAdapter
cons protected init(int,java.lang.String,int,java.lang.String,java.lang.String,org.objectweb.asm.MethodVisitor)
cons public init(java.lang.String,int,java.lang.String,java.lang.String,org.objectweb.asm.MethodVisitor)
fld public java.util.List locals
fld public java.util.List stack
fld public java.util.Map uninitializedTypes
meth public !varargs void visitInvokeDynamicInsn(java.lang.String,java.lang.String,org.objectweb.asm.Handle,java.lang.Object[])
meth public !varargs void visitTableSwitchInsn(int,int,org.objectweb.asm.Label,org.objectweb.asm.Label[])
meth public void visitFieldInsn(int,java.lang.String,java.lang.String,java.lang.String)
meth public void visitFrame(int,int,java.lang.Object[],int,java.lang.Object[])
meth public void visitIincInsn(int,int)
meth public void visitInsn(int)
meth public void visitIntInsn(int,int)
meth public void visitJumpInsn(int,org.objectweb.asm.Label)
meth public void visitLabel(org.objectweb.asm.Label)
meth public void visitLdcInsn(java.lang.Object)
meth public void visitLookupSwitchInsn(org.objectweb.asm.Label,int[],org.objectweb.asm.Label[])
meth public void visitMaxs(int,int)
meth public void visitMethodInsn(int,java.lang.String,java.lang.String,java.lang.String)
meth public void visitMultiANewArrayInsn(java.lang.String,int)
meth public void visitTypeInsn(int,java.lang.String)
meth public void visitVarInsn(int,int)
supr org.objectweb.asm.MethodVisitor
hfds labels,maxLocals,maxStack,owner

CLSS public org.objectweb.asm.commons.CodeSizeEvaluator
cons protected init(int,org.objectweb.asm.MethodVisitor)
cons public init(org.objectweb.asm.MethodVisitor)
intf org.objectweb.asm.Opcodes
meth public !varargs void visitInvokeDynamicInsn(java.lang.String,java.lang.String,org.objectweb.asm.Handle,java.lang.Object[])
meth public !varargs void visitTableSwitchInsn(int,int,org.objectweb.asm.Label,org.objectweb.asm.Label[])
meth public int getMaxSize()
meth public int getMinSize()
meth public void visitFieldInsn(int,java.lang.String,java.lang.String,java.lang.String)
meth public void visitIincInsn(int,int)
meth public void visitInsn(int)
meth public void visitIntInsn(int,int)
meth public void visitJumpInsn(int,org.objectweb.asm.Label)
meth public void visitLdcInsn(java.lang.Object)
meth public void visitLookupSwitchInsn(org.objectweb.asm.Label,int[],org.objectweb.asm.Label[])
meth public void visitMethodInsn(int,java.lang.String,java.lang.String,java.lang.String)
meth public void visitMultiANewArrayInsn(java.lang.String,int)
meth public void visitTypeInsn(int,java.lang.String)
meth public void visitVarInsn(int,int)
supr org.objectweb.asm.MethodVisitor
hfds maxSize,minSize

CLSS public org.objectweb.asm.commons.GeneratorAdapter
cons protected init(int,org.objectweb.asm.MethodVisitor,int,java.lang.String,java.lang.String)
cons public init(int,org.objectweb.asm.commons.Method,java.lang.String,org.objectweb.asm.Type[],org.objectweb.asm.ClassVisitor)
cons public init(int,org.objectweb.asm.commons.Method,org.objectweb.asm.MethodVisitor)
cons public init(org.objectweb.asm.MethodVisitor,int,java.lang.String,java.lang.String)
fld public final static int ADD = 96
fld public final static int AND = 126
fld public final static int DIV = 108
fld public final static int EQ = 153
fld public final static int GE = 156
fld public final static int GT = 157
fld public final static int LE = 158
fld public final static int LT = 155
fld public final static int MUL = 104
fld public final static int NE = 154
fld public final static int NEG = 116
fld public final static int OR = 128
fld public final static int REM = 112
fld public final static int SHL = 120
fld public final static int SHR = 122
fld public final static int SUB = 100
fld public final static int USHR = 124
fld public final static int XOR = 130
meth protected void setLocalType(int,org.objectweb.asm.Type)
meth public !varargs void invokeDynamic(java.lang.String,java.lang.String,org.objectweb.asm.Handle,java.lang.Object[])
meth public org.objectweb.asm.Label mark()
meth public org.objectweb.asm.Label newLabel()
meth public org.objectweb.asm.Type getLocalType(int)
meth public void arrayLength()
meth public void arrayLoad(org.objectweb.asm.Type)
meth public void arrayStore(org.objectweb.asm.Type)
meth public void box(org.objectweb.asm.Type)
meth public void cast(org.objectweb.asm.Type,org.objectweb.asm.Type)
meth public void catchException(org.objectweb.asm.Label,org.objectweb.asm.Label,org.objectweb.asm.Type)
meth public void checkCast(org.objectweb.asm.Type)
meth public void dup()
meth public void dup2()
meth public void dup2X1()
meth public void dup2X2()
meth public void dupX1()
meth public void dupX2()
meth public void endMethod()
meth public void getField(org.objectweb.asm.Type,java.lang.String,org.objectweb.asm.Type)
meth public void getStatic(org.objectweb.asm.Type,java.lang.String,org.objectweb.asm.Type)
meth public void goTo(org.objectweb.asm.Label)
meth public void ifCmp(org.objectweb.asm.Type,int,org.objectweb.asm.Label)
meth public void ifICmp(int,org.objectweb.asm.Label)
meth public void ifNonNull(org.objectweb.asm.Label)
meth public void ifNull(org.objectweb.asm.Label)
meth public void ifZCmp(int,org.objectweb.asm.Label)
meth public void iinc(int,int)
meth public void instanceOf(org.objectweb.asm.Type)
meth public void invokeConstructor(org.objectweb.asm.Type,org.objectweb.asm.commons.Method)
meth public void invokeInterface(org.objectweb.asm.Type,org.objectweb.asm.commons.Method)
meth public void invokeStatic(org.objectweb.asm.Type,org.objectweb.asm.commons.Method)
meth public void invokeVirtual(org.objectweb.asm.Type,org.objectweb.asm.commons.Method)
meth public void loadArg(int)
meth public void loadArgArray()
meth public void loadArgs()
meth public void loadArgs(int,int)
meth public void loadLocal(int)
meth public void loadLocal(int,org.objectweb.asm.Type)
meth public void loadThis()
meth public void mark(org.objectweb.asm.Label)
meth public void math(int,org.objectweb.asm.Type)
meth public void monitorEnter()
meth public void monitorExit()
meth public void newArray(org.objectweb.asm.Type)
meth public void newInstance(org.objectweb.asm.Type)
meth public void not()
meth public void pop()
meth public void pop2()
meth public void push(boolean)
meth public void push(double)
meth public void push(float)
meth public void push(int)
meth public void push(java.lang.String)
meth public void push(long)
meth public void push(org.objectweb.asm.Handle)
meth public void push(org.objectweb.asm.Type)
meth public void putField(org.objectweb.asm.Type,java.lang.String,org.objectweb.asm.Type)
meth public void putStatic(org.objectweb.asm.Type,java.lang.String,org.objectweb.asm.Type)
meth public void ret(int)
meth public void returnValue()
meth public void storeArg(int)
meth public void storeLocal(int)
meth public void storeLocal(int,org.objectweb.asm.Type)
meth public void swap()
meth public void swap(org.objectweb.asm.Type,org.objectweb.asm.Type)
meth public void tableSwitch(int[],org.objectweb.asm.commons.TableSwitchGenerator)
meth public void tableSwitch(int[],org.objectweb.asm.commons.TableSwitchGenerator,boolean)
meth public void throwException()
meth public void throwException(org.objectweb.asm.Type,java.lang.String)
meth public void unbox(org.objectweb.asm.Type)
meth public void valueOf(org.objectweb.asm.Type)
supr org.objectweb.asm.commons.LocalVariablesSorter
hfds BOOLEAN_TYPE,BOOLEAN_VALUE,BYTE_TYPE,CHARACTER_TYPE,CHAR_VALUE,CLDESC,DOUBLE_TYPE,DOUBLE_VALUE,FLOAT_TYPE,FLOAT_VALUE,INTEGER_TYPE,INT_VALUE,LONG_TYPE,LONG_VALUE,NUMBER_TYPE,OBJECT_TYPE,SHORT_TYPE,access,argumentTypes,localTypes,returnType

CLSS public org.objectweb.asm.commons.InstructionAdapter
cons protected init(int,org.objectweb.asm.MethodVisitor)
cons public init(org.objectweb.asm.MethodVisitor)
fld public final static org.objectweb.asm.Type OBJECT_TYPE
meth public !varargs void tableswitch(int,int,org.objectweb.asm.Label,org.objectweb.asm.Label[])
meth public !varargs void visitInvokeDynamicInsn(java.lang.String,java.lang.String,org.objectweb.asm.Handle,java.lang.Object[])
meth public !varargs void visitTableSwitchInsn(int,int,org.objectweb.asm.Label,org.objectweb.asm.Label[])
meth public void aconst(java.lang.Object)
meth public void add(org.objectweb.asm.Type)
meth public void aload(org.objectweb.asm.Type)
meth public void and(org.objectweb.asm.Type)
meth public void anew(org.objectweb.asm.Type)
meth public void areturn(org.objectweb.asm.Type)
meth public void arraylength()
meth public void astore(org.objectweb.asm.Type)
meth public void athrow()
meth public void cast(org.objectweb.asm.Type,org.objectweb.asm.Type)
meth public void checkcast(org.objectweb.asm.Type)
meth public void cmpg(org.objectweb.asm.Type)
meth public void cmpl(org.objectweb.asm.Type)
meth public void dconst(double)
meth public void div(org.objectweb.asm.Type)
meth public void dup()
meth public void dup2()
meth public void dup2X1()
meth public void dup2X2()
meth public void dupX1()
meth public void dupX2()
meth public void fconst(float)
meth public void getfield(java.lang.String,java.lang.String,java.lang.String)
meth public void getstatic(java.lang.String,java.lang.String,java.lang.String)
meth public void goTo(org.objectweb.asm.Label)
meth public void hconst(org.objectweb.asm.Handle)
meth public void iconst(int)
meth public void ifacmpeq(org.objectweb.asm.Label)
meth public void ifacmpne(org.objectweb.asm.Label)
meth public void ifeq(org.objectweb.asm.Label)
meth public void ifge(org.objectweb.asm.Label)
meth public void ifgt(org.objectweb.asm.Label)
meth public void ificmpeq(org.objectweb.asm.Label)
meth public void ificmpge(org.objectweb.asm.Label)
meth public void ificmpgt(org.objectweb.asm.Label)
meth public void ificmple(org.objectweb.asm.Label)
meth public void ificmplt(org.objectweb.asm.Label)
meth public void ificmpne(org.objectweb.asm.Label)
meth public void ifle(org.objectweb.asm.Label)
meth public void iflt(org.objectweb.asm.Label)
meth public void ifne(org.objectweb.asm.Label)
meth public void ifnonnull(org.objectweb.asm.Label)
meth public void ifnull(org.objectweb.asm.Label)
meth public void iinc(int,int)
meth public void instanceOf(org.objectweb.asm.Type)
meth public void invokedynamic(java.lang.String,java.lang.String,org.objectweb.asm.Handle,java.lang.Object[])
meth public void invokeinterface(java.lang.String,java.lang.String,java.lang.String)
meth public void invokespecial(java.lang.String,java.lang.String,java.lang.String)
meth public void invokestatic(java.lang.String,java.lang.String,java.lang.String)
meth public void invokevirtual(java.lang.String,java.lang.String,java.lang.String)
meth public void jsr(org.objectweb.asm.Label)
meth public void lcmp()
meth public void lconst(long)
meth public void load(int,org.objectweb.asm.Type)
meth public void lookupswitch(org.objectweb.asm.Label,int[],org.objectweb.asm.Label[])
meth public void mark(org.objectweb.asm.Label)
meth public void monitorenter()
meth public void monitorexit()
meth public void mul(org.objectweb.asm.Type)
meth public void multianewarray(java.lang.String,int)
meth public void neg(org.objectweb.asm.Type)
meth public void newarray(org.objectweb.asm.Type)
meth public void nop()
meth public void or(org.objectweb.asm.Type)
meth public void pop()
meth public void pop2()
meth public void putfield(java.lang.String,java.lang.String,java.lang.String)
meth public void putstatic(java.lang.String,java.lang.String,java.lang.String)
meth public void rem(org.objectweb.asm.Type)
meth public void ret(int)
meth public void shl(org.objectweb.asm.Type)
meth public void shr(org.objectweb.asm.Type)
meth public void store(int,org.objectweb.asm.Type)
meth public void sub(org.objectweb.asm.Type)
meth public void swap()
meth public void tconst(org.objectweb.asm.Type)
meth public void ushr(org.objectweb.asm.Type)
meth public void visitFieldInsn(int,java.lang.String,java.lang.String,java.lang.String)
meth public void visitIincInsn(int,int)
meth public void visitInsn(int)
meth public void visitIntInsn(int,int)
meth public void visitJumpInsn(int,org.objectweb.asm.Label)
meth public void visitLabel(org.objectweb.asm.Label)
meth public void visitLdcInsn(java.lang.Object)
meth public void visitLookupSwitchInsn(org.objectweb.asm.Label,int[],org.objectweb.asm.Label[])
meth public void visitMethodInsn(int,java.lang.String,java.lang.String,java.lang.String)
meth public void visitMultiANewArrayInsn(java.lang.String,int)
meth public void visitTypeInsn(int,java.lang.String)
meth public void visitVarInsn(int,int)
meth public void xor(org.objectweb.asm.Type)
supr org.objectweb.asm.MethodVisitor

CLSS public org.objectweb.asm.commons.JSRInlinerAdapter
cons protected init(int,org.objectweb.asm.MethodVisitor,int,java.lang.String,java.lang.String,java.lang.String,java.lang.String[])
cons public init(org.objectweb.asm.MethodVisitor,int,java.lang.String,java.lang.String,java.lang.String,java.lang.String[])
intf org.objectweb.asm.Opcodes
meth public void visitEnd()
meth public void visitJumpInsn(int,org.objectweb.asm.Label)
supr org.objectweb.asm.tree.MethodNode
hfds dualCitizens,mainSubroutine,subroutineHeads

CLSS public org.objectweb.asm.commons.LocalVariablesSorter
cons protected init(int,int,java.lang.String,org.objectweb.asm.MethodVisitor)
cons public init(int,java.lang.String,org.objectweb.asm.MethodVisitor)
fld protected final int firstLocal
fld protected int nextLocal
meth protected int newLocalMapping(org.objectweb.asm.Type)
meth protected void setLocalType(int,org.objectweb.asm.Type)
meth public int newLocal(org.objectweb.asm.Type)
meth public void visitFrame(int,int,java.lang.Object[],int,java.lang.Object[])
meth public void visitIincInsn(int,int)
meth public void visitLocalVariable(java.lang.String,java.lang.String,java.lang.String,org.objectweb.asm.Label,org.objectweb.asm.Label,int)
meth public void visitMaxs(int,int)
meth public void visitVarInsn(int,int)
supr org.objectweb.asm.MethodVisitor
hfds OBJECT_TYPE,changed,mapping,newLocals

CLSS public org.objectweb.asm.commons.Method
cons public init(java.lang.String,java.lang.String)
cons public init(java.lang.String,org.objectweb.asm.Type,org.objectweb.asm.Type[])
meth public boolean equals(java.lang.Object)
meth public int hashCode()
meth public java.lang.String getDescriptor()
meth public java.lang.String getName()
meth public java.lang.String toString()
meth public org.objectweb.asm.Type getReturnType()
meth public org.objectweb.asm.Type[] getArgumentTypes()
meth public static org.objectweb.asm.commons.Method getMethod(java.lang.String)
meth public static org.objectweb.asm.commons.Method getMethod(java.lang.String,boolean)
meth public static org.objectweb.asm.commons.Method getMethod(java.lang.reflect.Constructor)
meth public static org.objectweb.asm.commons.Method getMethod(java.lang.reflect.Method)
supr java.lang.Object
hfds DESCRIPTORS,desc,name

CLSS public abstract org.objectweb.asm.commons.Remapper
cons public init()
meth protected org.objectweb.asm.signature.SignatureVisitor createRemappingSignatureAdapter(org.objectweb.asm.signature.SignatureVisitor)
meth public java.lang.Object mapValue(java.lang.Object)
meth public java.lang.String map(java.lang.String)
meth public java.lang.String mapDesc(java.lang.String)
meth public java.lang.String mapFieldName(java.lang.String,java.lang.String,java.lang.String)
meth public java.lang.String mapInvokeDynamicMethodName(java.lang.String,java.lang.String)
meth public java.lang.String mapMethodDesc(java.lang.String)
meth public java.lang.String mapMethodName(java.lang.String,java.lang.String,java.lang.String)
meth public java.lang.String mapSignature(java.lang.String,boolean)
meth public java.lang.String mapType(java.lang.String)
meth public java.lang.String[] mapTypes(java.lang.String[])
supr java.lang.Object

CLSS public org.objectweb.asm.commons.RemappingAnnotationAdapter
cons protected init(int,org.objectweb.asm.AnnotationVisitor,org.objectweb.asm.commons.Remapper)
cons public init(org.objectweb.asm.AnnotationVisitor,org.objectweb.asm.commons.Remapper)
fld protected final org.objectweb.asm.commons.Remapper remapper
meth public org.objectweb.asm.AnnotationVisitor visitAnnotation(java.lang.String,java.lang.String)
meth public org.objectweb.asm.AnnotationVisitor visitArray(java.lang.String)
meth public void visit(java.lang.String,java.lang.Object)
meth public void visitEnum(java.lang.String,java.lang.String,java.lang.String)
supr org.objectweb.asm.AnnotationVisitor

CLSS public org.objectweb.asm.commons.RemappingClassAdapter
cons protected init(int,org.objectweb.asm.ClassVisitor,org.objectweb.asm.commons.Remapper)
cons public init(org.objectweb.asm.ClassVisitor,org.objectweb.asm.commons.Remapper)
fld protected final org.objectweb.asm.commons.Remapper remapper
fld protected java.lang.String className
meth protected org.objectweb.asm.AnnotationVisitor createRemappingAnnotationAdapter(org.objectweb.asm.AnnotationVisitor)
meth protected org.objectweb.asm.FieldVisitor createRemappingFieldAdapter(org.objectweb.asm.FieldVisitor)
meth protected org.objectweb.asm.MethodVisitor createRemappingMethodAdapter(int,java.lang.String,org.objectweb.asm.MethodVisitor)
meth public org.objectweb.asm.AnnotationVisitor visitAnnotation(java.lang.String,boolean)
meth public org.objectweb.asm.FieldVisitor visitField(int,java.lang.String,java.lang.String,java.lang.String,java.lang.Object)
meth public org.objectweb.asm.MethodVisitor visitMethod(int,java.lang.String,java.lang.String,java.lang.String,java.lang.String[])
meth public void visit(int,int,java.lang.String,java.lang.String,java.lang.String,java.lang.String[])
meth public void visitInnerClass(java.lang.String,java.lang.String,java.lang.String,int)
meth public void visitOuterClass(java.lang.String,java.lang.String,java.lang.String)
supr org.objectweb.asm.ClassVisitor

CLSS public org.objectweb.asm.commons.RemappingFieldAdapter
cons protected init(int,org.objectweb.asm.FieldVisitor,org.objectweb.asm.commons.Remapper)
cons public init(org.objectweb.asm.FieldVisitor,org.objectweb.asm.commons.Remapper)
meth public org.objectweb.asm.AnnotationVisitor visitAnnotation(java.lang.String,boolean)
supr org.objectweb.asm.FieldVisitor
hfds remapper

CLSS public org.objectweb.asm.commons.RemappingMethodAdapter
cons protected init(int,int,java.lang.String,org.objectweb.asm.MethodVisitor,org.objectweb.asm.commons.Remapper)
cons public init(int,java.lang.String,org.objectweb.asm.MethodVisitor,org.objectweb.asm.commons.Remapper)
fld protected final org.objectweb.asm.commons.Remapper remapper
meth public !varargs void visitInvokeDynamicInsn(java.lang.String,java.lang.String,org.objectweb.asm.Handle,java.lang.Object[])
meth public org.objectweb.asm.AnnotationVisitor visitAnnotation(java.lang.String,boolean)
meth public org.objectweb.asm.AnnotationVisitor visitAnnotationDefault()
meth public org.objectweb.asm.AnnotationVisitor visitParameterAnnotation(int,java.lang.String,boolean)
meth public void visitFieldInsn(int,java.lang.String,java.lang.String,java.lang.String)
meth public void visitFrame(int,int,java.lang.Object[],int,java.lang.Object[])
meth public void visitLdcInsn(java.lang.Object)
meth public void visitLocalVariable(java.lang.String,java.lang.String,java.lang.String,org.objectweb.asm.Label,org.objectweb.asm.Label,int)
meth public void visitMethodInsn(int,java.lang.String,java.lang.String,java.lang.String)
meth public void visitMultiANewArrayInsn(java.lang.String,int)
meth public void visitTryCatchBlock(org.objectweb.asm.Label,org.objectweb.asm.Label,org.objectweb.asm.Label,java.lang.String)
meth public void visitTypeInsn(int,java.lang.String)
supr org.objectweb.asm.commons.LocalVariablesSorter

CLSS public org.objectweb.asm.commons.RemappingSignatureAdapter
cons protected init(int,org.objectweb.asm.signature.SignatureVisitor,org.objectweb.asm.commons.Remapper)
cons public init(org.objectweb.asm.signature.SignatureVisitor,org.objectweb.asm.commons.Remapper)
meth public org.objectweb.asm.signature.SignatureVisitor visitArrayType()
meth public org.objectweb.asm.signature.SignatureVisitor visitClassBound()
meth public org.objectweb.asm.signature.SignatureVisitor visitExceptionType()
meth public org.objectweb.asm.signature.SignatureVisitor visitInterface()
meth public org.objectweb.asm.signature.SignatureVisitor visitInterfaceBound()
meth public org.objectweb.asm.signature.SignatureVisitor visitParameterType()
meth public org.objectweb.asm.signature.SignatureVisitor visitReturnType()
meth public org.objectweb.asm.signature.SignatureVisitor visitSuperclass()
meth public org.objectweb.asm.signature.SignatureVisitor visitTypeArgument(char)
meth public void visitBaseType(char)
meth public void visitClassType(java.lang.String)
meth public void visitEnd()
meth public void visitFormalTypeParameter(java.lang.String)
meth public void visitInnerClassType(java.lang.String)
meth public void visitTypeArgument()
meth public void visitTypeVariable(java.lang.String)
supr org.objectweb.asm.signature.SignatureVisitor
hfds className,remapper,v

CLSS public org.objectweb.asm.commons.SerialVersionUIDAdder
cons protected init(int,org.objectweb.asm.ClassVisitor)
cons public init(org.objectweb.asm.ClassVisitor)
meth protected byte[] computeSHAdigest(byte[])
meth protected long computeSVUID() throws java.io.IOException
meth public org.objectweb.asm.FieldVisitor visitField(int,java.lang.String,java.lang.String,java.lang.String,java.lang.Object)
meth public org.objectweb.asm.MethodVisitor visitMethod(int,java.lang.String,java.lang.String,java.lang.String,java.lang.String[])
meth public void visit(int,int,java.lang.String,java.lang.String,java.lang.String,java.lang.String[])
meth public void visitEnd()
meth public void visitInnerClass(java.lang.String,java.lang.String,java.lang.String,int)
supr org.objectweb.asm.ClassVisitor
hfds access,computeSVUID,hasSVUID,hasStaticInitializer,interfaces,name,svuidConstructors,svuidFields,svuidMethods

CLSS public org.objectweb.asm.commons.SimpleRemapper
cons public init(java.lang.String,java.lang.String)
cons public init(java.util.Map)
meth public java.lang.String map(java.lang.String)
meth public java.lang.String mapFieldName(java.lang.String,java.lang.String,java.lang.String)
meth public java.lang.String mapMethodName(java.lang.String,java.lang.String,java.lang.String)
supr org.objectweb.asm.commons.Remapper
hfds mapping

CLSS public org.objectweb.asm.commons.StaticInitMerger
cons protected init(int,java.lang.String,org.objectweb.asm.ClassVisitor)
cons public init(java.lang.String,org.objectweb.asm.ClassVisitor)
meth public org.objectweb.asm.MethodVisitor visitMethod(int,java.lang.String,java.lang.String,java.lang.String,java.lang.String[])
meth public void visit(int,int,java.lang.String,java.lang.String,java.lang.String,java.lang.String[])
meth public void visitEnd()
supr org.objectweb.asm.ClassVisitor
hfds clinit,counter,name,prefix

CLSS public abstract interface org.objectweb.asm.commons.TableSwitchGenerator
meth public abstract void generateCase(int,org.objectweb.asm.Label)
meth public abstract void generateDefault()

CLSS public org.objectweb.asm.commons.TryCatchBlockSorter
cons protected init(int,org.objectweb.asm.MethodVisitor,int,java.lang.String,java.lang.String,java.lang.String,java.lang.String[])
cons public init(org.objectweb.asm.MethodVisitor,int,java.lang.String,java.lang.String,java.lang.String,java.lang.String[])
meth public void visitEnd()
supr org.objectweb.asm.tree.MethodNode

CLSS public abstract org.objectweb.asm.signature.SignatureVisitor
cons public init(int)
fld protected final int api
fld public final static char EXTENDS = '+'
fld public final static char INSTANCEOF = '='
fld public final static char SUPER = '-'
meth public org.objectweb.asm.signature.SignatureVisitor visitArrayType()
meth public org.objectweb.asm.signature.SignatureVisitor visitClassBound()
meth public org.objectweb.asm.signature.SignatureVisitor visitExceptionType()
meth public org.objectweb.asm.signature.SignatureVisitor visitInterface()
meth public org.objectweb.asm.signature.SignatureVisitor visitInterfaceBound()
meth public org.objectweb.asm.signature.SignatureVisitor visitParameterType()
meth public org.objectweb.asm.signature.SignatureVisitor visitReturnType()
meth public org.objectweb.asm.signature.SignatureVisitor visitSuperclass()
meth public org.objectweb.asm.signature.SignatureVisitor visitTypeArgument(char)
meth public void visitBaseType(char)
meth public void visitClassType(java.lang.String)
meth public void visitEnd()
meth public void visitFormalTypeParameter(java.lang.String)
meth public void visitInnerClassType(java.lang.String)
meth public void visitTypeArgument()
meth public void visitTypeVariable(java.lang.String)
supr java.lang.Object

CLSS public org.objectweb.asm.tree.MethodNode
cons public init()
cons public init(int)
cons public init(int,int,java.lang.String,java.lang.String,java.lang.String,java.lang.String[])
cons public init(int,java.lang.String,java.lang.String,java.lang.String,java.lang.String[])
fld public int access
fld public int maxLocals
fld public int maxStack
fld public java.lang.Object annotationDefault
fld public java.lang.String desc
fld public java.lang.String name
fld public java.lang.String signature
fld public java.util.List attrs
fld public java.util.List exceptions
fld public java.util.List invisibleAnnotations
fld public java.util.List localVariables
fld public java.util.List tryCatchBlocks
fld public java.util.List visibleAnnotations
fld public java.util.List[] invisibleParameterAnnotations
fld public java.util.List[] visibleParameterAnnotations
fld public org.objectweb.asm.tree.InsnList instructions
meth protected org.objectweb.asm.tree.LabelNode getLabelNode(org.objectweb.asm.Label)
meth public !varargs void visitInvokeDynamicInsn(java.lang.String,java.lang.String,org.objectweb.asm.Handle,java.lang.Object[])
meth public !varargs void visitTableSwitchInsn(int,int,org.objectweb.asm.Label,org.objectweb.asm.Label[])
meth public org.objectweb.asm.AnnotationVisitor visitAnnotation(java.lang.String,boolean)
meth public org.objectweb.asm.AnnotationVisitor visitAnnotationDefault()
meth public org.objectweb.asm.AnnotationVisitor visitParameterAnnotation(int,java.lang.String,boolean)
meth public void accept(org.objectweb.asm.ClassVisitor)
meth public void accept(org.objectweb.asm.MethodVisitor)
meth public void check(int)
meth public void visitAttribute(org.objectweb.asm.Attribute)
meth public void visitCode()
meth public void visitEnd()
meth public void visitFieldInsn(int,java.lang.String,java.lang.String,java.lang.String)
meth public void visitFrame(int,int,java.lang.Object[],int,java.lang.Object[])
meth public void visitIincInsn(int,int)
meth public void visitInsn(int)
meth public void visitIntInsn(int,int)
meth public void visitJumpInsn(int,org.objectweb.asm.Label)
meth public void visitLabel(org.objectweb.asm.Label)
meth public void visitLdcInsn(java.lang.Object)
meth public void visitLineNumber(int,org.objectweb.asm.Label)
meth public void visitLocalVariable(java.lang.String,java.lang.String,java.lang.String,org.objectweb.asm.Label,org.objectweb.asm.Label,int)
meth public void visitLookupSwitchInsn(org.objectweb.asm.Label,int[],org.objectweb.asm.Label[])
meth public void visitMaxs(int,int)
meth public void visitMethodInsn(int,java.lang.String,java.lang.String,java.lang.String)
meth public void visitMultiANewArrayInsn(java.lang.String,int)
meth public void visitTryCatchBlock(org.objectweb.asm.Label,org.objectweb.asm.Label,org.objectweb.asm.Label,java.lang.String)
meth public void visitTypeInsn(int,java.lang.String)
meth public void visitVarInsn(int,int)
supr org.objectweb.asm.MethodVisitor
hfds visited

